MickeNet/PyGPGlib.py
MickeNet/__init__.py
PyGpgLib-0.1.6.dist-info/METADATA
PyGpgLib-0.1.6.dist-info/WHEEL
PyGpgLib-0.1.6.dist-info/top_level.txt
PyGpgLib-0.1.6.dist-info/RECORD
