Metadata-Version: 2.1
Name: PyGpgLib
Version: 0.1.6
Summary: A custom wrapper to pgp.
Author-email: Mickael Eriksson <mickael@felis-it.com>
Classifier: Programming Language :: Python :: 3
Classifier: License :: OSI Approved :: MIT License
Classifier: Operating System :: OS Independent
Requires-Python: >=3.7
